maxstdio.pyd
maxstdio-0.2.dist-info/DESCRIPTION.rst
maxstdio-0.2.dist-info/METADATA
maxstdio-0.2.dist-info/RECORD
maxstdio-0.2.dist-info/WHEEL
maxstdio-0.2.dist-info/metadata.json
maxstdio-0.2.dist-info/top_level.txt
